CHANGELOG.md
xenterval/__init__.py
xenterval/_primes.py
xenterval/_ratios.py
xenterval/_xenwiki.py
xenterval/interval/__init__.py
xenterval/interval/name/__init__.py
xenterval/interval/name/color.py
xenterval/interval/name/fjs.py
xenterval/ji.py
xenterval/py.typed
xenterval/tuning.py
xenterval/typing.py
xenterval-0.2.1.dist-info/LICENSE
xenterval-0.2.1.dist-info/WHEEL
xenterval-0.2.1.dist-info/METADATA
xenterval-0.2.1.dist-info/RECORD
